EduData/__init__.py
EduData/main.py
EduData/DataSet/__init__.py
EduData/DataSet/EdNet/KnowledgeTracing.py
EduData/DataSet/EdNet/__init__.py
EduData/DataSet/EdNet/utils.py
EduData/DataSet/download_data/__init__.py
EduData/DataSet/download_data/download_data.py
EduData/DataSet/download_data/utils.py
EduData/DataSet/junyi/KnowledgeTracing.py
EduData/DataSet/junyi/__init__.py
EduData/DataSet/junyi/junyi.py
EduData/DataSet/junyi/main.py
EduData/DataSet/synthetic/KnowledgeTracing.py
EduData/DataSet/synthetic/__init__.py
EduData/Task/__init__.py
EduData/Task/KnowledgeTracing/__init__.py
EduData/Task/KnowledgeTracing/format.py
EduData/Task/KnowledgeTracing/graph.py
EduData/Task/KnowledgeTracing/statistics.py
tests/__init__.py
tests/conftest.py
tests/test_download.py
tests/test_ednet.py
tests/test_format.py
tests/test_graph.py
tests/test_junyi.py
tests/test_statics.py
tests/test_synthetic.py
EduData-0.0.18.dist-info/AUTHORS.md
EduData-0.0.18.dist-info/LICENSE
EduData-0.0.18.dist-info/METADATA
EduData-0.0.18.dist-info/WHEEL
EduData-0.0.18.dist-info/entry_points.txt
EduData-0.0.18.dist-info/top_level.txt
EduData-0.0.18.dist-info/RECORD
