Metadata-Version: 2.1
Name: EduData
Version: 0.0.18
Summary: This project aims to provide convenient interfaces for downloading and preprocessing dataset in education.
Home-page: UNKNOWN
License: UNKNOWN
Platform: UNKNOWN
Requires-Python: >=3.6
Requires-Dist: tqdm
Requires-Dist: networkx
Requires-Dist: longling[ml] (>=1.3.15)
Requires-Dist: requests
Requires-Dist: bs4
Requires-Dist: rarfile
Requires-Dist: pandas
Requires-Dist: fire
Requires-Dist: lxml
Requires-Dist: numpy (>=1.16.5)
Requires-Dist: scipy (>=1.2.0)
Requires-Dist: scikit-learn (>=0.23.2)
Provides-Extra: test
Requires-Dist: pytest (>=4) ; extra == 'test'
Requires-Dist: pytest-cov (>=2.6.0) ; extra == 'test'
Requires-Dist: pytest-flake8 ; extra == 'test'
